{"func_ov039_021111a0": {}, "func_ov039_021111d0": {}, "func_ov039_02111214": {}, "func_ov039_02111254": {}, "func_ov039_02111278": {}, "func_ov039_021112a0": {"disasm": ["  push    {r4, r5, r6, r7, r8, sb, sl, lr}", "  mov     r4, r0", "  add     r0, r4, #0x74", "  add     r1, r4, #0x5c", "  bl      #0xfff2bd3c  ; -> Vec3_Dist", "  mov     sl, r0", "  ldr     r0, [pc, #0x68]  ; = 0x13a", "  mov     r1, #0", "  mov     sb, #1", "  mov     r8, #2", "  bl      #0xffeffc50  ; -> _ZN5Actor15FindWithActorIDEjPS_", "  movs    r7, r0", "  beq     #0x6c", "  ldr     r5, [pc, #0x4c]  ; = 0x13a", "  add     r6, r4, #0x74", "  cmp     r7, r4", "  beq     #0x58", "  mov     r0, r6", "  add     r1, r7, #0x5c", "  bl      #0xfff2bd3c  ; -> Vec3_Dist", "  cmp     sl, r0", "  addgt   sb, sb, #1", "  mov     r0, r5", "  mov     r1, r7", "  bl      #0xffeffc50  ; -> _ZN5Actor15FindWithActorIDEjPS_", "  movs    r7, r0", "  bne     #0x3c", "  add     r1, r8, sb", "  add     r0, r4, #0xd4", "  and     r1, r1, #0xff", "  bl      #0xfff0581c  ; -> _ZN5Model12SetPolygonIDEi", "  mov     r0, #1", "  pop     {r4, r5, r6, r7, r8, sb, sl, lr}", "  bx      lr", "  andeq   r0, r0, sl, lsr r1"], "pool": [{"off": "0x88", "const": "0x13a"}, {"off": "0x88", "const": "0x13a"}], "draft": "extern int Vec3_Dist(void* a, void* b);\nextern void* FindWithActorID(unsigned int id, void* prev);\nextern int SetPolygonID(void* model, int id);\nint func_ov039_021112a0(char *c) {\n    int d = Vec3_Dist(c+0x74, c+0x5c);\n    int rank = 1;\n    void *a = FindWithActorID(0x13a, 0);\n    while (a) {\n        if (a != (void*)c) {\n            int d2 = Vec3_Dist(c+0x74, (char*)a+0x5c);\n            if (d > d2) rank++;\n        }\n        a = FindWithActorID(0x13a, a);\n    }\n    SetPolygonID(c+0xd4, (2 + rank) & 0xff);\n    return 1;\n}\n", "draftDiv": 28}, "func_ov039_0211132c": {}, "func_ov039_0211137c": {}, "__sinit_ov039_021113b4": {}}